htmxapp/__init__.py
htmxapp/forms/__init__.py
htmxapp/forms/base_form.py
htmxapp/forms/decorators.py
htmxapp/forms/form.py
htmxapp-0.0.0.dist-info/METADATA
htmxapp-0.0.0.dist-info/WHEEL
htmxapp-0.0.0.dist-info/RECORD
